poet_plugin/__init__.py
poet_plugin/plugin.py
matsight_poet_plugin-0.1.2.dist-info/LICENSE
matsight_poet_plugin-0.1.2.dist-info/METADATA
matsight_poet_plugin-0.1.2.dist-info/WHEEL
matsight_poet_plugin-0.1.2.dist-info/entry_points.txt
matsight_poet_plugin-0.1.2.dist-info/RECORD
