Metadata-Version: 2.3
Name: matsight-poet-plugin
Version: 0.1.2
Summary: A Poetry plugin to enable exclusivity between groups
License: MIT
Author: Idan Tene
Author-email: idan.tene@gmail.com
Requires-Python: >=3.9,<4.0
Classifier: License :: OSI Approved :: MIT License
Classifier: Programming Language :: Python :: 3
Classifier: Programming Language :: Python :: 3.9
Classifier: Programming Language :: Python :: 3.10
Classifier: Programming Language :: Python :: 3.11
Classifier: Programming Language :: Python :: 3.12
Classifier: Programming Language :: Python :: 3.13
Requires-Dist: poetry (>=2.0.0,<3.0.0)
